{
  "$schema": "https://json-schema.org/draft/2020-12/schema",
  "$id": "https://recomby.ai/schemas/brief_meta.schema.json",
  "title": "Brief meta",
  "description": "briefs/<id>.meta.json — written by 04-content-brief Step 7, read by 05-production's status gate and by geo-review-html. The status field is the human-in-loop production gate: 05-production refuses to run unless status is exactly 'ready-for-production'.",
  "type": "object",
  "required": ["priority_id", "status", "slots"],
  "additionalProperties": true,
  "properties": {
    "priority_id": { "type": "string", "minLength": 1 },
    "brief_path": { "type": "string" },
    "generated_at": { "type": "string" },
    "format": { "type": "string", "description": "Recommended content format; surfaced in the review HTML header." },
    "word_count": { "type": "integer", "minimum": 0 },
    "status": {
      "type": "string",
      "enum": ["awaiting-expert-fill", "ready-for-production"],
      "description": "awaiting-expert-fill: REQUIRED-FILL slots not all filled; ready-for-production: all slots filled and verified by 04 Step 9 — the only value 05-production accepts. Lowercase-hyphen, case-sensitive."
    },
    "slots": {
      "type": "array",
      "description": "One entry per REQUIRED-FILL slot in the brief.",
      "items": {
        "type": "object",
        "required": ["id", "filled"],
        "additionalProperties": true,
        "properties": {
          "id": { "type": "string", "minLength": 1 },
          "type": { "type": "string" },
          "filled": { "type": "boolean" }
        }
      }
    },
    "expert_assignee": { "type": ["string", "null"] },
    "due_at": { "type": ["string", "null"] }
  }
}
